linode_mcp/__init__.py
linode_mcp/server.py
linode_mcp/tools/__init__.py
linode_mcp/tools/linode_tools.py
linode_mcp_fastmcp-0.0.2.dist-info/licenses/LICENSE
linode_mcp_fastmcp-0.0.2.dist-info/METADATA
linode_mcp_fastmcp-0.0.2.dist-info/WHEEL
linode_mcp_fastmcp-0.0.2.dist-info/entry_points.txt
linode_mcp_fastmcp-0.0.2.dist-info/top_level.txt
linode_mcp_fastmcp-0.0.2.dist-info/RECORD
